sarya/UI.py
sarya/__init__.py
sarya/client.py
sarya/constant.py
sarya/settings.py
sarya_sdk-0.0.2.6.dist-info/LICENSE
sarya_sdk-0.0.2.6.dist-info/METADATA
sarya_sdk-0.0.2.6.dist-info/WHEEL
sarya_sdk-0.0.2.6.dist-info/RECORD
