Metadata-Version: 2.1
Name: sarya-sdk
Version: 0.0.2.6
Summary: Sarya SDK to ingerate your Persona with Sarya Users
Author: Khalid Alrasheed
Author-email: khalid@cycls.io
Requires-Python: >=3.10,<4.0
Classifier: Programming Language :: Python :: 3
Classifier: Programming Language :: Python :: 3.10
Classifier: Programming Language :: Python :: 3.11
Requires-Dist: asyncio (>=3.4.3,<4.0.0)
Requires-Dist: fastapi (>=0.104.1,<0.105.0)
Requires-Dist: httpx (>=0.25.1,<0.26.0)
Requires-Dist: pydantic-settings (>=2.1.0,<3.0.0)
Requires-Dist: uvicorn (>=0.24.0,<0.25.0)
